{
  "ip": "193.219.28.18",
  "asn": "9200",
  "neighbors": [
    {
      "ip": "193.219.28.162",
      "asn": "85"
    },
    {
      "ip": "212.191.229.49",
      "asn": "262"
    },
    {
      "ip": "213.135.50.51",
      "asn": "72"
    },
    {
      "ip": "213.135.50.52",
      "asn": "103"
    },
    {
      "ip": "213.135.50.54",
      "asn": "38"
    },
    {
      "ip": "213.135.50.55",
      "asn": "18"
    },
    {
      "ip": "213.135.52.64",
      "asn": "21"
    },
    {
      "ip": "213.135.52.66",
      "asn": "21"
    },
    {
      "ip": "2001:6a0::2",
      "asn": "22"
    },
    {
      "ip": "2001:6a0::4",
      "asn": "20"
    },
    {
      "ip": "2001:6a0:0:40::1",
      "asn": "20"
    },
    {
      "ip": "2001:b10:c000:304::1",
      "asn": "243"
    }
  ]
}